{
  "case_id": "case_0615",
  "points": [
    [
      -309479.0,
      934999.0
    ],
    [
      -483185.0,
      -242107.0
    ],
    [
      996804.0,
      702415.0
    ],
    [
      61921.0,
      834121.0
    ],
    [
      985008.0,
      450974.0
    ],
    [
      -476351.0,
      -324603.0
    ],
    [
      -734866.0,
      -41110.0
    ],
    [
      502485.0,
      -70691.0
    ],
    [
      296009.0,
      412779.0
    ],
    [
      -526719.0,
      -632179.0
    ],
    [
      -641776.0,
      -233985.0
    ],
    [
      -699587.0,
      -682395.0
    ],
    [
      52765.0,
      -252177.0
    ],
    [
      -616550.0,
      -170926.0
    ],
    [
      465527.0,
      95769.0
    ],
    [
      -576466.0,
      -712210.0
    ],
    [
      -622934.0,
      -470598.0
    ],
    [
      -505285.0,
      615494.0
    ],
    [
      598834.0,
      387633.0
    ],
    [
      491376.0,
      -710407.0
    ],
    [
      353647.0,
      -788116.0
    ],
    [
      203650.0,
      944474.0
    ],
    [
      -99118.0,
      804635.0
    ],
    [
      373819.0,
      -676480.0
    ],
    [
      -788140.0,
      -776310.0
    ]
  ],
  "expected": {
    "peel_order": [
      [
        996804.0,
        702415.0
      ],
      [
        985008.0,
        450974.0
      ],
      [
        598834.0,
        387633.0
      ],
      [
        203650.0,
        944474.0
      ],
      [
        -788140.0,
        -776310.0
      ],
      [
        -734866.0,
        -41110.0
      ],
      [
        -505285.0,
        615494.0
      ],
      [
        -309479.0,
        934999.0
      ],
      [
        -99118.0,
        804635.0
      ],
      [
        61921.0,
        834121.0
      ],
      [
        296009.0,
        412779.0
      ],
      [
        465527.0,
        95769.0
      ],
      [
        502485.0,
        -70691.0
      ],
      [
        52765.0,
        -252177.0
      ],
      [
        353647.0,
        -788116.0
      ],
      [
        491376.0,
        -710407.0
      ],
      [
        373819.0,
        -676480.0
      ],
      [
        -699587.0,
        -682395.0
      ],
      [
        -576466.0,
        -712210.0
      ],
      [
        -526719.0,
        -632179.0
      ],
      [
        -622934.0,
        -470598.0
      ],
      [
        -476351.0,
        -324603.0
      ]
    ],
    "area_decreases": [
      101143381439.0,
      328648433930.0,
      139546127331.5,
      100842141032.0,
      74995812122.0,
      79148242630.0,
      61361764059.5,
      154202679636.0,
      70923183963.5,
      260568885109.0,
      194119416390.0,
      94989525615.0,
      221844226678.0,
      135531315044.5,
      41366304295.5,
      31135896660.0,
      212146585331.0,
      25244921497.5,
      7869176336.0,
      18865968324.0,
      18717140584.5,
      6513808694.0
    ],
    "hulls": [
      [
        [
          -788140.0,
          -776310.0
        ],
        [
          353647.0,
          -788116.0
        ],
        [
          491376.0,
          -710407.0
        ],
        [
          985008.0,
          450974.0
        ],
        [
          996804.0,
          702415.0
        ],
        [
          203650.0,
          944474.0
        ],
        [
          -309479.0,
          934999.0
        ],
        [
          -505285.0,
          615494.0
        ],
        [
          -734866.0,
          -41110.0
        ]
      ],
      [
        [
          -788140.0,
          -776310.0
        ],
        [
          353647.0,
          -788116.0
        ],
        [
          491376.0,
          -710407.0
        ],
        [
          985008.0,
          450974.0
        ],
        [
          203650.0,
          944474.0
        ],
        [
          -309479.0,
          934999.0
        ],
        [
          -505285.0,
          615494.0
        ],
        [
          -734866.0,
          -41110.0
        ]
      ],
      [
        [
          -788140.0,
          -776310.0
        ],
        [
          353647.0,
          -788116.0
        ],
        [
          491376.0,
          -710407.0
        ],
        [
          598834.0,
          387633.0
        ],
        [
          203650.0,
          944474.0
        ],
        [
          -309479.0,
          934999.0
        ],
        [
          -505285.0,
          615494.0
        ],
        [
          -734866.0,
          -41110.0
        ]
      ],
      [
        [
          -788140.0,
          -776310.0
        ],
        [
          353647.0,
          -788116.0
        ],
        [
          491376.0,
          -710407.0
        ],
        [
          502485.0,
          -70691.0
        ],
        [
          465527.0,
          95769.0
        ],
        [
          203650.0,
          944474.0
        ],
        [
          -309479.0,
          934999.0
        ],
        [
          -505285.0,
          615494.0
        ],
        [
          -734866.0,
          -41110.0
        ]
      ],
      [
        [
          -788140.0,
          -776310.0
        ],
        [
          353647.0,
          -788116.0
        ],
        [
          491376.0,
          -710407.0
        ],
        [
          502485.0,
          -70691.0
        ],
        [
          465527.0,
          95769.0
        ],
        [
          296009.0,
          412779.0
        ],
        [
          61921.0,
          834121.0
        ],
        [
          -309479.0,
          934999.0
        ],
        [
          -505285.0,
          615494.0
        ],
        [
          -734866.0,
          -41110.0
        ]
      ],
      [
        [
          -734866.0,
          -41110.0
        ],
        [
          -699587.0,
          -682395.0
        ],
        [
          -576466.0,
          -712210.0
        ],
        [
          353647.0,
          -788116.0
        ],
        [
          491376.0,
          -710407.0
        ],
        [
          502485.0,
          -70691.0
        ],
        [
          465527.0,
          95769.0
        ],
        [
          296009.0,
          412779.0
        ],
        [
          61921.0,
          834121.0
        ],
        [
          -309479.0,
          934999.0
        ],
        [
          -505285.0,
          615494.0
        ]
      ],
      [
        [
          -699587.0,
          -682395.0
        ],
        [
          -576466.0,
          -712210.0
        ],
        [
          353647.0,
          -788116.0
        ],
        [
          491376.0,
          -710407.0
        ],
        [
          502485.0,
          -70691.0
        ],
        [
          465527.0,
          95769.0
        ],
        [
          296009.0,
          412779.0
        ],
        [
          61921.0,
          834121.0
        ],
        [
          -309479.0,
          934999.0
        ],
        [
          -505285.0,
          615494.0
        ],
        [
          -641776.0,
          -233985.0
        ]
      ],
      [
        [
          -699587.0,
          -682395.0
        ],
        [
          -576466.0,
          -712210.0
        ],
        [
          353647.0,
          -788116.0
        ],
        [
          491376.0,
          -710407.0
        ],
        [
          502485.0,
          -70691.0
        ],
        [
          465527.0,
          95769.0
        ],
        [
          296009.0,
          412779.0
        ],
        [
          61921.0,
          834121.0
        ],
        [
          -309479.0,
          934999.0
        ],
        [
          -641776.0,
          -233985.0
        ]
      ],
      [
        [
          -699587.0,
          -682395.0
        ],
        [
          -576466.0,
          -712210.0
        ],
        [
          353647.0,
          -788116.0
        ],
        [
          491376.0,
          -710407.0
        ],
        [
          502485.0,
          -70691.0
        ],
        [
          465527.0,
          95769.0
        ],
        [
          296009.0,
          412779.0
        ],
        [
          61921.0,
          834121.0
        ],
        [
          -99118.0,
          804635.0
        ],
        [
          -616550.0,
          -170926.0
        ],
        [
          -641776.0,
          -233985.0
        ]
      ],
      [
        [
          -699587.0,
          -682395.0
        ],
        [
          -576466.0,
          -712210.0
        ],
        [
          353647.0,
          -788116.0
        ],
        [
          491376.0,
          -710407.0
        ],
        [
          502485.0,
          -70691.0
        ],
        [
          465527.0,
          95769.0
        ],
        [
          296009.0,
          412779.0
        ],
        [
          61921.0,
          834121.0
        ],
        [
          -616550.0,
          -170926.0
        ],
        [
          -641776.0,
          -233985.0
        ]
      ],
      [
        [
          -699587.0,
          -682395.0
        ],
        [
          -576466.0,
          -712210.0
        ],
        [
          353647.0,
          -788116.0
        ],
        [
          491376.0,
          -710407.0
        ],
        [
          502485.0,
          -70691.0
        ],
        [
          465527.0,
          95769.0
        ],
        [
          296009.0,
          412779.0
        ],
        [
          -616550.0,
          -170926.0
        ],
        [
          -641776.0,
          -233985.0
        ]
      ],
      [
        [
          -699587.0,
          -682395.0
        ],
        [
          -576466.0,
          -712210.0
        ],
        [
          353647.0,
          -788116.0
        ],
        [
          491376.0,
          -710407.0
        ],
        [
          502485.0,
          -70691.0
        ],
        [
          465527.0,
          95769.0
        ],
        [
          -616550.0,
          -170926.0
        ],
        [
          -641776.0,
          -233985.0
        ]
      ],
      [
        [
          -699587.0,
          -682395.0
        ],
        [
          -576466.0,
          -712210.0
        ],
        [
          353647.0,
          -788116.0
        ],
        [
          491376.0,
          -710407.0
        ],
        [
          502485.0,
          -70691.0
        ],
        [
          -616550.0,
          -170926.0
        ],
        [
          -641776.0,
          -233985.0
        ]
      ],
      [
        [
          -699587.0,
          -682395.0
        ],
        [
          -576466.0,
          -712210.0
        ],
        [
          353647.0,
          -788116.0
        ],
        [
          491376.0,
          -710407.0
        ],
        [
          52765.0,
          -252177.0
        ],
        [
          -616550.0,
          -170926.0
        ],
        [
          -641776.0,
          -233985.0
        ]
      ],
      [
        [
          -699587.0,
          -682395.0
        ],
        [
          -576466.0,
          -712210.0
        ],
        [
          353647.0,
          -788116.0
        ],
        [
          491376.0,
          -710407.0
        ],
        [
          -616550.0,
          -170926.0
        ],
        [
          -641776.0,
          -233985.0
        ]
      ],
      [
        [
          -699587.0,
          -682395.0
        ],
        [
          -576466.0,
          -712210.0
        ],
        [
          491376.0,
          -710407.0
        ],
        [
          -616550.0,
          -170926.0
        ],
        [
          -641776.0,
          -233985.0
        ]
      ],
      [
        [
          -699587.0,
          -682395.0
        ],
        [
          -576466.0,
          -712210.0
        ],
        [
          373819.0,
          -676480.0
        ],
        [
          -616550.0,
          -170926.0
        ],
        [
          -641776.0,
          -233985.0
        ]
      ],
      [
        [
          -699587.0,
          -682395.0
        ],
        [
          -576466.0,
          -712210.0
        ],
        [
          -526719.0,
          -632179.0
        ],
        [
          -476351.0,
          -324603.0
        ],
        [
          -483185.0,
          -242107.0
        ],
        [
          -616550.0,
          -170926.0
        ],
        [
          -641776.0,
          -233985.0
        ]
      ],
      [
        [
          -641776.0,
          -233985.0
        ],
        [
          -622934.0,
          -470598.0
        ],
        [
          -576466.0,
          -712210.0
        ],
        [
          -526719.0,
          -632179.0
        ],
        [
          -476351.0,
          -324603.0
        ],
        [
          -483185.0,
          -242107.0
        ],
        [
          -616550.0,
          -170926.0
        ]
      ],
      [
        [
          -641776.0,
          -233985.0
        ],
        [
          -622934.0,
          -470598.0
        ],
        [
          -526719.0,
          -632179.0
        ],
        [
          -476351.0,
          -324603.0
        ],
        [
          -483185.0,
          -242107.0
        ],
        [
          -616550.0,
          -170926.0
        ]
      ],
      [
        [
          -641776.0,
          -233985.0
        ],
        [
          -622934.0,
          -470598.0
        ],
        [
          -476351.0,
          -324603.0
        ],
        [
          -483185.0,
          -242107.0
        ],
        [
          -616550.0,
          -170926.0
        ]
      ],
      [
        [
          -641776.0,
          -233985.0
        ],
        [
          -476351.0,
          -324603.0
        ],
        [
          -483185.0,
          -242107.0
        ],
        [
          -616550.0,
          -170926.0
        ]
      ]
    ],
    "final_points": [
      [
        -483185.0,
        -242107.0
      ],
      [
        -641776.0,
        -233985.0
      ],
      [
        -616550.0,
        -170926.0
      ]
    ],
    "layers_after_peel": [
      [
        [
          [
            -788140.0,
            -776310.0
          ],
          [
            353647.0,
            -788116.0
          ],
          [
            491376.0,
            -710407.0
          ],
          [
            985008.0,
            450974.0
          ],
          [
            203650.0,
            944474.0
          ],
          [
            -309479.0,
            934999.0
          ],
          [
            -505285.0,
            615494.0
          ],
          [
            -734866.0,
            -41110.0
          ]
        ],
        [
          [
            -699587.0,
            -682395.0
          ],
          [
            -576466.0,
            -712210.0
          ],
          [
            373819.0,
            -676480.0
          ],
          [
            502485.0,
            -70691.0
          ],
          [
            598834.0,
            387633.0
          ],
          [
            61921.0,
            834121.0
          ],
          [
            -99118.0,
            804635.0
          ],
          [
            -616550.0,
            -170926.0
          ],
          [
            -641776.0,
            -233985.0
          ]
        ],
        [
          [
            -622934.0,
            -470598.0
          ],
          [
            -526719.0,
            -632179.0
          ],
          [
            52765.0,
            -252177.0
          ],
          [
            465527.0,
            95769.0
          ],
          [
            296009.0,
            412779.0
          ],
          [
            -483185.0,
            -242107.0
          ]
        ],
        [
          [
            -476351.0,
            -324603.0
          ]
        ]
      ],
      [
        [
          [
            -788140.0,
            -776310.0
          ],
          [
            353647.0,
            -788116.0
          ],
          [
            491376.0,
            -710407.0
          ],
          [
            598834.0,
            387633.0
          ],
          [
            203650.0,
            944474.0
          ],
          [
            -309479.0,
            934999.0
          ],
          [
            -505285.0,
            615494.0
          ],
          [
            -734866.0,
            -41110.0
          ]
        ],
        [
          [
            -699587.0,
            -682395.0
          ],
          [
            -576466.0,
            -712210.0
          ],
          [
            373819.0,
            -676480.0
          ],
          [
            502485.0,
            -70691.0
          ],
          [
            465527.0,
            95769.0
          ],
          [
            296009.0,
            412779.0
          ],
          [
            61921.0,
            834121.0
          ],
          [
            -99118.0,
            804635.0
          ],
          [
            -616550.0,
            -170926.0
          ],
          [
            -641776.0,
            -233985.0
          ]
        ],
        [
          [
            -622934.0,
            -470598.0
          ],
          [
            -526719.0,
            -632179.0
          ],
          [
            52765.0,
            -252177.0
          ],
          [
            -483185.0,
            -242107.0
          ]
        ],
        [
          [
            -476351.0,
            -324603.0
          ]
        ]
      ],
      [
        [
          [
            -788140.0,
            -776310.0
          ],
          [
            353647.0,
            -788116.0
          ],
          [
            491376.0,
            -710407.0
          ],
          [
            502485.0,
            -70691.0
          ],
          [
            465527.0,
            95769.0
          ],
          [
            203650.0,
            944474.0
          ],
          [
            -309479.0,
            934999.0
          ],
          [
            -505285.0,
            615494.0
          ],
          [
            -734866.0,
            -41110.0
          ]
        ],
        [
          [
            -699587.0,
            -682395.0
          ],
          [
            -576466.0,
            -712210.0
          ],
          [
            373819.0,
            -676480.0
          ],
          [
            296009.0,
            412779.0
          ],
          [
            61921.0,
            834121.0
          ],
          [
            -99118.0,
            804635.0
          ],
          [
            -616550.0,
            -170926.0
          ],
          [
            -641776.0,
            -233985.0
          ]
        ],
        [
          [
            -622934.0,
            -470598.0
          ],
          [
            -526719.0,
            -632179.0
          ],
          [
            52765.0,
            -252177.0
          ],
          [
            -483185.0,
            -242107.0
          ]
        ],
        [
          [
            -476351.0,
            -324603.0
          ]
        ]
      ],
      [
        [
          [
            -788140.0,
            -776310.0
          ],
          [
            353647.0,
            -788116.0
          ],
          [
            491376.0,
            -710407.0
          ],
          [
            502485.0,
            -70691.0
          ],
          [
            465527.0,
            95769.0
          ],
          [
            296009.0,
            412779.0
          ],
          [
            61921.0,
            834121.0
          ],
          [
            -309479.0,
            934999.0
          ],
          [
            -505285.0,
            615494.0
          ],
          [
            -734866.0,
            -41110.0
          ]
        ],
        [
          [
            -699587.0,
            -682395.0
          ],
          [
            -576466.0,
            -712210.0
          ],
          [
            373819.0,
            -676480.0
          ],
          [
            -99118.0,
            804635.0
          ],
          [
            -616550.0,
            -170926.0
          ],
          [
            -641776.0,
            -233985.0
          ]
        ],
        [
          [
            -622934.0,
            -470598.0
          ],
          [
            -526719.0,
            -632179.0
          ],
          [
            52765.0,
            -252177.0
          ],
          [
            -483185.0,
            -242107.0
          ]
        ],
        [
          [
            -476351.0,
            -324603.0
          ]
        ]
      ],
      [
        [
          [
            -734866.0,
            -41110.0
          ],
          [
            -699587.0,
            -682395.0
          ],
          [
            -576466.0,
            -712210.0
          ],
          [
            353647.0,
            -788116.0
          ],
          [
            491376.0,
            -710407.0
          ],
          [
            502485.0,
            -70691.0
          ],
          [
            465527.0,
            95769.0
          ],
          [
            296009.0,
            412779.0
          ],
          [
            61921.0,
            834121.0
          ],
          [
            -309479.0,
            934999.0
          ],
          [
            -505285.0,
            615494.0
          ]
        ],
        [
          [
            -641776.0,
            -233985.0
          ],
          [
            -622934.0,
            -470598.0
          ],
          [
            -526719.0,
            -632179.0
          ],
          [
            373819.0,
            -676480.0
          ],
          [
            -99118.0,
            804635.0
          ],
          [
            -616550.0,
            -170926.0
          ]
        ],
        [
          [
            -483185.0,
            -242107.0
          ],
          [
            -476351.0,
            -324603.0
          ],
          [
            52765.0,
            -252177.0
          ]
        ]
      ],
      [
        [
          [
            -699587.0,
            -682395.0
          ],
          [
            -576466.0,
            -712210.0
          ],
          [
            353647.0,
            -788116.0
          ],
          [
            491376.0,
            -710407.0
          ],
          [
            502485.0,
            -70691.0
          ],
          [
            465527.0,
            95769.0
          ],
          [
            296009.0,
            412779.0
          ],
          [
            61921.0,
            834121.0
          ],
          [
            -309479.0,
            934999.0
          ],
          [
            -505285.0,
            615494.0
          ],
          [
            -641776.0,
            -233985.0
          ]
        ],
        [
          [
            -622934.0,
            -470598.0
          ],
          [
            -526719.0,
            -632179.0
          ],
          [
            373819.0,
            -676480.0
          ],
          [
            -99118.0,
            804635.0
          ],
          [
            -616550.0,
            -170926.0
          ]
        ],
        [
          [
            -483185.0,
            -242107.0
          ],
          [
            -476351.0,
            -324603.0
          ],
          [
            52765.0,
            -252177.0
          ]
        ]
      ],
      [
        [
          [
            -699587.0,
            -682395.0
          ],
          [
            -576466.0,
            -712210.0
          ],
          [
            353647.0,
            -788116.0
          ],
          [
            491376.0,
            -710407.0
          ],
          [
            502485.0,
            -70691.0
          ],
          [
            465527.0,
            95769.0
          ],
          [
            296009.0,
            412779.0
          ],
          [
            61921.0,
            834121.0
          ],
          [
            -309479.0,
            934999.0
          ],
          [
            -641776.0,
            -233985.0
          ]
        ],
        [
          [
            -622934.0,
            -470598.0
          ],
          [
            -526719.0,
            -632179.0
          ],
          [
            373819.0,
            -676480.0
          ],
          [
            -99118.0,
            804635.0
          ],
          [
            -616550.0,
            -170926.0
          ]
        ],
        [
          [
            -483185.0,
            -242107.0
          ],
          [
            -476351.0,
            -324603.0
          ],
          [
            52765.0,
            -252177.0
          ]
        ]
      ],
      [
        [
          [
            -699587.0,
            -682395.0
          ],
          [
            -576466.0,
            -712210.0
          ],
          [
            353647.0,
            -788116.0
          ],
          [
            491376.0,
            -710407.0
          ],
          [
            502485.0,
            -70691.0
          ],
          [
            465527.0,
            95769.0
          ],
          [
            296009.0,
            412779.0
          ],
          [
            61921.0,
            834121.0
          ],
          [
            -99118.0,
            804635.0
          ],
          [
            -616550.0,
            -170926.0
          ],
          [
            -641776.0,
            -233985.0
          ]
        ],
        [
          [
            -622934.0,
            -470598.0
          ],
          [
            -526719.0,
            -632179.0
          ],
          [
            373819.0,
            -676480.0
          ],
          [
            52765.0,
            -252177.0
          ],
          [
            -483185.0,
            -242107.0
          ]
        ],
        [
          [
            -476351.0,
            -324603.0
          ]
        ]
      ],
      [
        [
          [
            -699587.0,
            -682395.0
          ],
          [
            -576466.0,
            -712210.0
          ],
          [
            353647.0,
            -788116.0
          ],
          [
            491376.0,
            -710407.0
          ],
          [
            502485.0,
            -70691.0
          ],
          [
            465527.0,
            95769.0
          ],
          [
            296009.0,
            412779.0
          ],
          [
            61921.0,
            834121.0
          ],
          [
            -616550.0,
            -170926.0
          ],
          [
            -641776.0,
            -233985.0
          ]
        ],
        [
          [
            -622934.0,
            -470598.0
          ],
          [
            -526719.0,
            -632179.0
          ],
          [
            373819.0,
            -676480.0
          ],
          [
            52765.0,
            -252177.0
          ],
          [
            -483185.0,
            -242107.0
          ]
        ],
        [
          [
            -476351.0,
            -324603.0
          ]
        ]
      ],
      [
        [
          [
            -699587.0,
            -682395.0
          ],
          [
            -576466.0,
            -712210.0
          ],
          [
            353647.0,
            -788116.0
          ],
          [
            491376.0,
            -710407.0
          ],
          [
            502485.0,
            -70691.0
          ],
          [
            465527.0,
            95769.0
          ],
          [
            296009.0,
            412779.0
          ],
          [
            -616550.0,
            -170926.0
          ],
          [
            -641776.0,
            -233985.0
          ]
        ],
        [
          [
            -622934.0,
            -470598.0
          ],
          [
            -526719.0,
            -632179.0
          ],
          [
            373819.0,
            -676480.0
          ],
          [
            52765.0,
            -252177.0
          ],
          [
            -483185.0,
            -242107.0
          ]
        ],
        [
          [
            -476351.0,
            -324603.0
          ]
        ]
      ],
      [
        [
          [
            -699587.0,
            -682395.0
          ],
          [
            -576466.0,
            -712210.0
          ],
          [
            353647.0,
            -788116.0
          ],
          [
            491376.0,
            -710407.0
          ],
          [
            502485.0,
            -70691.0
          ],
          [
            465527.0,
            95769.0
          ],
          [
            -616550.0,
            -170926.0
          ],
          [
            -641776.0,
            -233985.0
          ]
        ],
        [
          [
            -622934.0,
            -470598.0
          ],
          [
            -526719.0,
            -632179.0
          ],
          [
            373819.0,
            -676480.0
          ],
          [
            52765.0,
            -252177.0
          ],
          [
            -483185.0,
            -242107.0
          ]
        ],
        [
          [
            -476351.0,
            -324603.0
          ]
        ]
      ],
      [
        [
          [
            -699587.0,
            -682395.0
          ],
          [
            -576466.0,
            -712210.0
          ],
          [
            353647.0,
            -788116.0
          ],
          [
            491376.0,
            -710407.0
          ],
          [
            502485.0,
            -70691.0
          ],
          [
            -616550.0,
            -170926.0
          ],
          [
            -641776.0,
            -233985.0
          ]
        ],
        [
          [
            -622934.0,
            -470598.0
          ],
          [
            -526719.0,
            -632179.0
          ],
          [
            373819.0,
            -676480.0
          ],
          [
            52765.0,
            -252177.0
          ],
          [
            -483185.0,
            -242107.0
          ]
        ],
        [
          [
            -476351.0,
            -324603.0
          ]
        ]
      ],
      [
        [
          [
            -699587.0,
            -682395.0
          ],
          [
            -576466.0,
            -712210.0
          ],
          [
            353647.0,
            -788116.0
          ],
          [
            491376.0,
            -710407.0
          ],
          [
            52765.0,
            -252177.0
          ],
          [
            -616550.0,
            -170926.0
          ],
          [
            -641776.0,
            -233985.0
          ]
        ],
        [
          [
            -622934.0,
            -470598.0
          ],
          [
            -526719.0,
            -632179.0
          ],
          [
            373819.0,
            -676480.0
          ],
          [
            -483185.0,
            -242107.0
          ]
        ],
        [
          [
            -476351.0,
            -324603.0
          ]
        ]
      ],
      [
        [
          [
            -699587.0,
            -682395.0
          ],
          [
            -576466.0,
            -712210.0
          ],
          [
            353647.0,
            -788116.0
          ],
          [
            491376.0,
            -710407.0
          ],
          [
            -616550.0,
            -170926.0
          ],
          [
            -641776.0,
            -233985.0
          ]
        ],
        [
          [
            -622934.0,
            -470598.0
          ],
          [
            -526719.0,
            -632179.0
          ],
          [
            373819.0,
            -676480.0
          ],
          [
            -483185.0,
            -242107.0
          ]
        ],
        [
          [
            -476351.0,
            -324603.0
          ]
        ]
      ],
      [
        [
          [
            -699587.0,
            -682395.0
          ],
          [
            -576466.0,
            -712210.0
          ],
          [
            491376.0,
            -710407.0
          ],
          [
            -616550.0,
            -170926.0
          ],
          [
            -641776.0,
            -233985.0
          ]
        ],
        [
          [
            -622934.0,
            -470598.0
          ],
          [
            -526719.0,
            -632179.0
          ],
          [
            373819.0,
            -676480.0
          ],
          [
            -483185.0,
            -242107.0
          ]
        ],
        [
          [
            -476351.0,
            -324603.0
          ]
        ]
      ],
      [
        [
          [
            -699587.0,
            -682395.0
          ],
          [
            -576466.0,
            -712210.0
          ],
          [
            373819.0,
            -676480.0
          ],
          [
            -616550.0,
            -170926.0
          ],
          [
            -641776.0,
            -233985.0
          ]
        ],
        [
          [
            -622934.0,
            -470598.0
          ],
          [
            -526719.0,
            -632179.0
          ],
          [
            -476351.0,
            -324603.0
          ],
          [
            -483185.0,
            -242107.0
          ]
        ]
      ],
      [
        [
          [
            -699587.0,
            -682395.0
          ],
          [
            -576466.0,
            -712210.0
          ],
          [
            -526719.0,
            -632179.0
          ],
          [
            -476351.0,
            -324603.0
          ],
          [
            -483185.0,
            -242107.0
          ],
          [
            -616550.0,
            -170926.0
          ],
          [
            -641776.0,
            -233985.0
          ]
        ],
        [
          [
            -622934.0,
            -470598.0
          ]
        ]
      ],
      [
        [
          [
            -641776.0,
            -233985.0
          ],
          [
            -622934.0,
            -470598.0
          ],
          [
            -576466.0,
            -712210.0
          ],
          [
            -526719.0,
            -632179.0
          ],
          [
            -476351.0,
            -324603.0
          ],
          [
            -483185.0,
            -242107.0
          ],
          [
            -616550.0,
            -170926.0
          ]
        ]
      ],
      [
        [
          [
            -641776.0,
            -233985.0
          ],
          [
            -622934.0,
            -470598.0
          ],
          [
            -526719.0,
            -632179.0
          ],
          [
            -476351.0,
            -324603.0
          ],
          [
            -483185.0,
            -242107.0
          ],
          [
            -616550.0,
            -170926.0
          ]
        ]
      ],
      [
        [
          [
            -641776.0,
            -233985.0
          ],
          [
            -622934.0,
            -470598.0
          ],
          [
            -476351.0,
            -324603.0
          ],
          [
            -483185.0,
            -242107.0
          ],
          [
            -616550.0,
            -170926.0
          ]
        ]
      ],
      [
        [
          [
            -641776.0,
            -233985.0
          ],
          [
            -476351.0,
            -324603.0
          ],
          [
            -483185.0,
            -242107.0
          ],
          [
            -616550.0,
            -170926.0
          ]
        ]
      ],
      [
        [
          [
            -641776.0,
            -233985.0
          ],
          [
            -483185.0,
            -242107.0
          ],
          [
            -616550.0,
            -170926.0
          ]
        ]
      ]
    ]
  },
  "metadata": {
    "seed": 1614,
    "point_count": 25,
    "grid_limit": 1000000,
    "rejected_attempts": 0,
    "convex_hull_algorithm": "andrews_monotone_chain",
    "epsilons": {
      "orientation_epsilon": 1e-09,
      "min_area_decrease_epsilon": 1e-09
    },
    "source_suite": "v1_gold",
    "layer_snapshot_rule": "layers_after_peel"
  }
}
