{
  "case_id": "case_0231",
  "points": [
    [
      252012.0,
      -440318.0
    ],
    [
      448575.0,
      310579.0
    ],
    [
      -744121.0,
      993107.0
    ],
    [
      240954.0,
      759902.0
    ],
    [
      160478.0,
      679861.0
    ],
    [
      -25099.0,
      790631.0
    ],
    [
      438320.0,
      -934423.0
    ],
    [
      101642.0,
      348527.0
    ],
    [
      388361.0,
      -939945.0
    ],
    [
      -623686.0,
      992776.0
    ],
    [
      -72026.0,
      -883648.0
    ],
    [
      -317558.0,
      -753561.0
    ],
    [
      399678.0,
      832758.0
    ],
    [
      970472.0,
      406969.0
    ],
    [
      446542.0,
      146316.0
    ],
    [
      -426757.0,
      -628494.0
    ],
    [
      -101913.0,
      261028.0
    ],
    [
      723503.0,
      -387128.0
    ],
    [
      -410264.0,
      -147715.0
    ],
    [
      -31060.0,
      577821.0
    ],
    [
      356160.0,
      -448375.0
    ],
    [
      -139354.0,
      289054.0
    ],
    [
      883131.0,
      -560545.0
    ],
    [
      75525.0,
      -334881.0
    ],
    [
      -181206.0,
      -841971.0
    ]
  ],
  "expected": {
    "peel_order": [
      [
        970472.0,
        406969.0
      ],
      [
        399678.0,
        832758.0
      ],
      [
        883131.0,
        -560545.0
      ],
      [
        723503.0,
        -387128.0
      ],
      [
        -744121.0,
        993107.0
      ],
      [
        -623686.0,
        992776.0
      ],
      [
        -410264.0,
        -147715.0
      ],
      [
        -426757.0,
        -628494.0
      ],
      [
        -317558.0,
        -753561.0
      ],
      [
        -181206.0,
        -841971.0
      ],
      [
        -72026.0,
        -883648.0
      ],
      [
        -25099.0,
        790631.0
      ],
      [
        75525.0,
        -334881.0
      ],
      [
        388361.0,
        -939945.0
      ],
      [
        438320.0,
        -934423.0
      ],
      [
        252012.0,
        -440318.0
      ],
      [
        356160.0,
        -448375.0
      ],
      [
        446542.0,
        146316.0
      ],
      [
        448575.0,
        310579.0
      ],
      [
        101642.0,
        348527.0
      ],
      [
        -31060.0,
        577821.0
      ],
      [
        -101913.0,
        261028.0
      ]
    ],
    "area_decreases": [
      294720011582.5,
      178164990878.0,
      107453970087.5,
      174720447570.5,
      97596234475.5,
      398173566795.0,
      84851551478.5,
      87730121422.0,
      78958828060.0,
      62614787652.0,
      235466304427.0,
      39063310276.0,
      32586891202.0,
      32156801635.5,
      100541698867.5,
      36404699597.0,
      175125978107.0,
      45162036580.5,
      93043485179.0,
      35773888718.5,
      25689327952.0,
      14143765988.0
    ],
    "hulls": [
      [
        [
          -744121.0,
          993107.0
        ],
        [
          -426757.0,
          -628494.0
        ],
        [
          -317558.0,
          -753561.0
        ],
        [
          -181206.0,
          -841971.0
        ],
        [
          -72026.0,
          -883648.0
        ],
        [
          388361.0,
          -939945.0
        ],
        [
          438320.0,
          -934423.0
        ],
        [
          883131.0,
          -560545.0
        ],
        [
          970472.0,
          406969.0
        ],
        [
          399678.0,
          832758.0
        ],
        [
          -623686.0,
          992776.0
        ]
      ],
      [
        [
          -744121.0,
          993107.0
        ],
        [
          -426757.0,
          -628494.0
        ],
        [
          -317558.0,
          -753561.0
        ],
        [
          -181206.0,
          -841971.0
        ],
        [
          -72026.0,
          -883648.0
        ],
        [
          388361.0,
          -939945.0
        ],
        [
          438320.0,
          -934423.0
        ],
        [
          883131.0,
          -560545.0
        ],
        [
          399678.0,
          832758.0
        ],
        [
          -623686.0,
          992776.0
        ]
      ],
      [
        [
          -744121.0,
          993107.0
        ],
        [
          -426757.0,
          -628494.0
        ],
        [
          -317558.0,
          -753561.0
        ],
        [
          -181206.0,
          -841971.0
        ],
        [
          -72026.0,
          -883648.0
        ],
        [
          388361.0,
          -939945.0
        ],
        [
          438320.0,
          -934423.0
        ],
        [
          883131.0,
          -560545.0
        ],
        [
          240954.0,
          759902.0
        ],
        [
          -623686.0,
          992776.0
        ]
      ],
      [
        [
          -744121.0,
          993107.0
        ],
        [
          -426757.0,
          -628494.0
        ],
        [
          -317558.0,
          -753561.0
        ],
        [
          -181206.0,
          -841971.0
        ],
        [
          -72026.0,
          -883648.0
        ],
        [
          388361.0,
          -939945.0
        ],
        [
          438320.0,
          -934423.0
        ],
        [
          723503.0,
          -387128.0
        ],
        [
          448575.0,
          310579.0
        ],
        [
          240954.0,
          759902.0
        ],
        [
          -623686.0,
          992776.0
        ]
      ],
      [
        [
          -744121.0,
          993107.0
        ],
        [
          -426757.0,
          -628494.0
        ],
        [
          -317558.0,
          -753561.0
        ],
        [
          -181206.0,
          -841971.0
        ],
        [
          -72026.0,
          -883648.0
        ],
        [
          388361.0,
          -939945.0
        ],
        [
          438320.0,
          -934423.0
        ],
        [
          448575.0,
          310579.0
        ],
        [
          240954.0,
          759902.0
        ],
        [
          -623686.0,
          992776.0
        ]
      ],
      [
        [
          -623686.0,
          992776.0
        ],
        [
          -426757.0,
          -628494.0
        ],
        [
          -317558.0,
          -753561.0
        ],
        [
          -181206.0,
          -841971.0
        ],
        [
          -72026.0,
          -883648.0
        ],
        [
          388361.0,
          -939945.0
        ],
        [
          438320.0,
          -934423.0
        ],
        [
          448575.0,
          310579.0
        ],
        [
          240954.0,
          759902.0
        ]
      ],
      [
        [
          -426757.0,
          -628494.0
        ],
        [
          -317558.0,
          -753561.0
        ],
        [
          -181206.0,
          -841971.0
        ],
        [
          -72026.0,
          -883648.0
        ],
        [
          388361.0,
          -939945.0
        ],
        [
          438320.0,
          -934423.0
        ],
        [
          448575.0,
          310579.0
        ],
        [
          240954.0,
          759902.0
        ],
        [
          -25099.0,
          790631.0
        ],
        [
          -410264.0,
          -147715.0
        ]
      ],
      [
        [
          -426757.0,
          -628494.0
        ],
        [
          -317558.0,
          -753561.0
        ],
        [
          -181206.0,
          -841971.0
        ],
        [
          -72026.0,
          -883648.0
        ],
        [
          388361.0,
          -939945.0
        ],
        [
          438320.0,
          -934423.0
        ],
        [
          448575.0,
          310579.0
        ],
        [
          240954.0,
          759902.0
        ],
        [
          -25099.0,
          790631.0
        ]
      ],
      [
        [
          -317558.0,
          -753561.0
        ],
        [
          -181206.0,
          -841971.0
        ],
        [
          -72026.0,
          -883648.0
        ],
        [
          388361.0,
          -939945.0
        ],
        [
          438320.0,
          -934423.0
        ],
        [
          448575.0,
          310579.0
        ],
        [
          240954.0,
          759902.0
        ],
        [
          -25099.0,
          790631.0
        ],
        [
          -139354.0,
          289054.0
        ]
      ],
      [
        [
          -181206.0,
          -841971.0
        ],
        [
          -72026.0,
          -883648.0
        ],
        [
          388361.0,
          -939945.0
        ],
        [
          438320.0,
          -934423.0
        ],
        [
          448575.0,
          310579.0
        ],
        [
          240954.0,
          759902.0
        ],
        [
          -25099.0,
          790631.0
        ],
        [
          -139354.0,
          289054.0
        ]
      ],
      [
        [
          -139354.0,
          289054.0
        ],
        [
          -72026.0,
          -883648.0
        ],
        [
          388361.0,
          -939945.0
        ],
        [
          438320.0,
          -934423.0
        ],
        [
          448575.0,
          310579.0
        ],
        [
          240954.0,
          759902.0
        ],
        [
          -25099.0,
          790631.0
        ]
      ],
      [
        [
          -139354.0,
          289054.0
        ],
        [
          75525.0,
          -334881.0
        ],
        [
          388361.0,
          -939945.0
        ],
        [
          438320.0,
          -934423.0
        ],
        [
          448575.0,
          310579.0
        ],
        [
          240954.0,
          759902.0
        ],
        [
          -25099.0,
          790631.0
        ]
      ],
      [
        [
          -139354.0,
          289054.0
        ],
        [
          75525.0,
          -334881.0
        ],
        [
          388361.0,
          -939945.0
        ],
        [
          438320.0,
          -934423.0
        ],
        [
          448575.0,
          310579.0
        ],
        [
          240954.0,
          759902.0
        ],
        [
          -31060.0,
          577821.0
        ]
      ],
      [
        [
          -139354.0,
          289054.0
        ],
        [
          388361.0,
          -939945.0
        ],
        [
          438320.0,
          -934423.0
        ],
        [
          448575.0,
          310579.0
        ],
        [
          240954.0,
          759902.0
        ],
        [
          -31060.0,
          577821.0
        ]
      ],
      [
        [
          -139354.0,
          289054.0
        ],
        [
          438320.0,
          -934423.0
        ],
        [
          448575.0,
          310579.0
        ],
        [
          240954.0,
          759902.0
        ],
        [
          -31060.0,
          577821.0
        ]
      ],
      [
        [
          -139354.0,
          289054.0
        ],
        [
          252012.0,
          -440318.0
        ],
        [
          356160.0,
          -448375.0
        ],
        [
          446542.0,
          146316.0
        ],
        [
          448575.0,
          310579.0
        ],
        [
          240954.0,
          759902.0
        ],
        [
          -31060.0,
          577821.0
        ]
      ],
      [
        [
          -139354.0,
          289054.0
        ],
        [
          356160.0,
          -448375.0
        ],
        [
          446542.0,
          146316.0
        ],
        [
          448575.0,
          310579.0
        ],
        [
          240954.0,
          759902.0
        ],
        [
          -31060.0,
          577821.0
        ]
      ],
      [
        [
          -139354.0,
          289054.0
        ],
        [
          -101913.0,
          261028.0
        ],
        [
          446542.0,
          146316.0
        ],
        [
          448575.0,
          310579.0
        ],
        [
          240954.0,
          759902.0
        ],
        [
          -31060.0,
          577821.0
        ]
      ],
      [
        [
          -139354.0,
          289054.0
        ],
        [
          -101913.0,
          261028.0
        ],
        [
          448575.0,
          310579.0
        ],
        [
          240954.0,
          759902.0
        ],
        [
          -31060.0,
          577821.0
        ]
      ],
      [
        [
          -139354.0,
          289054.0
        ],
        [
          -101913.0,
          261028.0
        ],
        [
          101642.0,
          348527.0
        ],
        [
          240954.0,
          759902.0
        ],
        [
          -31060.0,
          577821.0
        ]
      ],
      [
        [
          -139354.0,
          289054.0
        ],
        [
          -101913.0,
          261028.0
        ],
        [
          240954.0,
          759902.0
        ],
        [
          -31060.0,
          577821.0
        ]
      ],
      [
        [
          -139354.0,
          289054.0
        ],
        [
          -101913.0,
          261028.0
        ],
        [
          240954.0,
          759902.0
        ],
        [
          160478.0,
          679861.0
        ]
      ]
    ],
    "final_points": [
      [
        240954.0,
        759902.0
      ],
      [
        160478.0,
        679861.0
      ],
      [
        -139354.0,
        289054.0
      ]
    ],
    "layers_after_peel": [
      [
        [
          [
            -744121.0,
            993107.0
          ],
          [
            -426757.0,
            -628494.0
          ],
          [
            -317558.0,
            -753561.0
          ],
          [
            -181206.0,
            -841971.0
          ],
          [
            -72026.0,
            -883648.0
          ],
          [
            388361.0,
            -939945.0
          ],
          [
            438320.0,
            -934423.0
          ],
          [
            883131.0,
            -560545.0
          ],
          [
            399678.0,
            832758.0
          ],
          [
            -623686.0,
            992776.0
          ]
        ],
        [
          [
            -410264.0,
            -147715.0
          ],
          [
            252012.0,
            -440318.0
          ],
          [
            356160.0,
            -448375.0
          ],
          [
            723503.0,
            -387128.0
          ],
          [
            448575.0,
            310579.0
          ],
          [
            240954.0,
            759902.0
          ],
          [
            -25099.0,
            790631.0
          ]
        ],
        [
          [
            -139354.0,
            289054.0
          ],
          [
            75525.0,
            -334881.0
          ],
          [
            446542.0,
            146316.0
          ],
          [
            160478.0,
            679861.0
          ],
          [
            -31060.0,
            577821.0
          ]
        ],
        [
          [
            -101913.0,
            261028.0
          ],
          [
            101642.0,
            348527.0
          ]
        ]
      ],
      [
        [
          [
            -744121.0,
            993107.0
          ],
          [
            -426757.0,
            -628494.0
          ],
          [
            -317558.0,
            -753561.0
          ],
          [
            -181206.0,
            -841971.0
          ],
          [
            -72026.0,
            -883648.0
          ],
          [
            388361.0,
            -939945.0
          ],
          [
            438320.0,
            -934423.0
          ],
          [
            883131.0,
            -560545.0
          ],
          [
            240954.0,
            759902.0
          ],
          [
            -623686.0,
            992776.0
          ]
        ],
        [
          [
            -410264.0,
            -147715.0
          ],
          [
            252012.0,
            -440318.0
          ],
          [
            356160.0,
            -448375.0
          ],
          [
            723503.0,
            -387128.0
          ],
          [
            448575.0,
            310579.0
          ],
          [
            160478.0,
            679861.0
          ],
          [
            -25099.0,
            790631.0
          ]
        ],
        [
          [
            -139354.0,
            289054.0
          ],
          [
            75525.0,
            -334881.0
          ],
          [
            446542.0,
            146316.0
          ],
          [
            -31060.0,
            577821.0
          ]
        ],
        [
          [
            -101913.0,
            261028.0
          ],
          [
            101642.0,
            348527.0
          ]
        ]
      ],
      [
        [
          [
            -744121.0,
            993107.0
          ],
          [
            -426757.0,
            -628494.0
          ],
          [
            -317558.0,
            -753561.0
          ],
          [
            -181206.0,
            -841971.0
          ],
          [
            -72026.0,
            -883648.0
          ],
          [
            388361.0,
            -939945.0
          ],
          [
            438320.0,
            -934423.0
          ],
          [
            723503.0,
            -387128.0
          ],
          [
            448575.0,
            310579.0
          ],
          [
            240954.0,
            759902.0
          ],
          [
            -623686.0,
            992776.0
          ]
        ],
        [
          [
            -410264.0,
            -147715.0
          ],
          [
            252012.0,
            -440318.0
          ],
          [
            356160.0,
            -448375.0
          ],
          [
            446542.0,
            146316.0
          ],
          [
            160478.0,
            679861.0
          ],
          [
            -25099.0,
            790631.0
          ]
        ],
        [
          [
            -139354.0,
            289054.0
          ],
          [
            75525.0,
            -334881.0
          ],
          [
            101642.0,
            348527.0
          ],
          [
            -31060.0,
            577821.0
          ]
        ],
        [
          [
            -101913.0,
            261028.0
          ]
        ]
      ],
      [
        [
          [
            -744121.0,
            993107.0
          ],
          [
            -426757.0,
            -628494.0
          ],
          [
            -317558.0,
            -753561.0
          ],
          [
            -181206.0,
            -841971.0
          ],
          [
            -72026.0,
            -883648.0
          ],
          [
            388361.0,
            -939945.0
          ],
          [
            438320.0,
            -934423.0
          ],
          [
            448575.0,
            310579.0
          ],
          [
            240954.0,
            759902.0
          ],
          [
            -623686.0,
            992776.0
          ]
        ],
        [
          [
            -410264.0,
            -147715.0
          ],
          [
            252012.0,
            -440318.0
          ],
          [
            356160.0,
            -448375.0
          ],
          [
            446542.0,
            146316.0
          ],
          [
            160478.0,
            679861.0
          ],
          [
            -25099.0,
            790631.0
          ]
        ],
        [
          [
            -139354.0,
            289054.0
          ],
          [
            75525.0,
            -334881.0
          ],
          [
            101642.0,
            348527.0
          ],
          [
            -31060.0,
            577821.0
          ]
        ],
        [
          [
            -101913.0,
            261028.0
          ]
        ]
      ],
      [
        [
          [
            -623686.0,
            992776.0
          ],
          [
            -426757.0,
            -628494.0
          ],
          [
            -317558.0,
            -753561.0
          ],
          [
            -181206.0,
            -841971.0
          ],
          [
            -72026.0,
            -883648.0
          ],
          [
            388361.0,
            -939945.0
          ],
          [
            438320.0,
            -934423.0
          ],
          [
            448575.0,
            310579.0
          ],
          [
            240954.0,
            759902.0
          ]
        ],
        [
          [
            -410264.0,
            -147715.0
          ],
          [
            252012.0,
            -440318.0
          ],
          [
            356160.0,
            -448375.0
          ],
          [
            446542.0,
            146316.0
          ],
          [
            160478.0,
            679861.0
          ],
          [
            -25099.0,
            790631.0
          ]
        ],
        [
          [
            -139354.0,
            289054.0
          ],
          [
            75525.0,
            -334881.0
          ],
          [
            101642.0,
            348527.0
          ],
          [
            -31060.0,
            577821.0
          ]
        ],
        [
          [
            -101913.0,
            261028.0
          ]
        ]
      ],
      [
        [
          [
            -426757.0,
            -628494.0
          ],
          [
            -317558.0,
            -753561.0
          ],
          [
            -181206.0,
            -841971.0
          ],
          [
            -72026.0,
            -883648.0
          ],
          [
            388361.0,
            -939945.0
          ],
          [
            438320.0,
            -934423.0
          ],
          [
            448575.0,
            310579.0
          ],
          [
            240954.0,
            759902.0
          ],
          [
            -25099.0,
            790631.0
          ],
          [
            -410264.0,
            -147715.0
          ]
        ],
        [
          [
            -139354.0,
            289054.0
          ],
          [
            75525.0,
            -334881.0
          ],
          [
            252012.0,
            -440318.0
          ],
          [
            356160.0,
            -448375.0
          ],
          [
            446542.0,
            146316.0
          ],
          [
            160478.0,
            679861.0
          ],
          [
            -31060.0,
            577821.0
          ]
        ],
        [
          [
            -101913.0,
            261028.0
          ],
          [
            101642.0,
            348527.0
          ]
        ]
      ],
      [
        [
          [
            -426757.0,
            -628494.0
          ],
          [
            -317558.0,
            -753561.0
          ],
          [
            -181206.0,
            -841971.0
          ],
          [
            -72026.0,
            -883648.0
          ],
          [
            388361.0,
            -939945.0
          ],
          [
            438320.0,
            -934423.0
          ],
          [
            448575.0,
            310579.0
          ],
          [
            240954.0,
            759902.0
          ],
          [
            -25099.0,
            790631.0
          ]
        ],
        [
          [
            -139354.0,
            289054.0
          ],
          [
            75525.0,
            -334881.0
          ],
          [
            252012.0,
            -440318.0
          ],
          [
            356160.0,
            -448375.0
          ],
          [
            446542.0,
            146316.0
          ],
          [
            160478.0,
            679861.0
          ],
          [
            -31060.0,
            577821.0
          ]
        ],
        [
          [
            -101913.0,
            261028.0
          ],
          [
            101642.0,
            348527.0
          ]
        ]
      ],
      [
        [
          [
            -317558.0,
            -753561.0
          ],
          [
            -181206.0,
            -841971.0
          ],
          [
            -72026.0,
            -883648.0
          ],
          [
            388361.0,
            -939945.0
          ],
          [
            438320.0,
            -934423.0
          ],
          [
            448575.0,
            310579.0
          ],
          [
            240954.0,
            759902.0
          ],
          [
            -25099.0,
            790631.0
          ],
          [
            -139354.0,
            289054.0
          ]
        ],
        [
          [
            -101913.0,
            261028.0
          ],
          [
            75525.0,
            -334881.0
          ],
          [
            252012.0,
            -440318.0
          ],
          [
            356160.0,
            -448375.0
          ],
          [
            446542.0,
            146316.0
          ],
          [
            160478.0,
            679861.0
          ],
          [
            -31060.0,
            577821.0
          ]
        ],
        [
          [
            101642.0,
            348527.0
          ]
        ]
      ],
      [
        [
          [
            -181206.0,
            -841971.0
          ],
          [
            -72026.0,
            -883648.0
          ],
          [
            388361.0,
            -939945.0
          ],
          [
            438320.0,
            -934423.0
          ],
          [
            448575.0,
            310579.0
          ],
          [
            240954.0,
            759902.0
          ],
          [
            -25099.0,
            790631.0
          ],
          [
            -139354.0,
            289054.0
          ]
        ],
        [
          [
            -101913.0,
            261028.0
          ],
          [
            75525.0,
            -334881.0
          ],
          [
            252012.0,
            -440318.0
          ],
          [
            356160.0,
            -448375.0
          ],
          [
            446542.0,
            146316.0
          ],
          [
            160478.0,
            679861.0
          ],
          [
            -31060.0,
            577821.0
          ]
        ],
        [
          [
            101642.0,
            348527.0
          ]
        ]
      ],
      [
        [
          [
            -139354.0,
            289054.0
          ],
          [
            -72026.0,
            -883648.0
          ],
          [
            388361.0,
            -939945.0
          ],
          [
            438320.0,
            -934423.0
          ],
          [
            448575.0,
            310579.0
          ],
          [
            240954.0,
            759902.0
          ],
          [
            -25099.0,
            790631.0
          ]
        ],
        [
          [
            -101913.0,
            261028.0
          ],
          [
            75525.0,
            -334881.0
          ],
          [
            252012.0,
            -440318.0
          ],
          [
            356160.0,
            -448375.0
          ],
          [
            446542.0,
            146316.0
          ],
          [
            160478.0,
            679861.0
          ],
          [
            -31060.0,
            577821.0
          ]
        ],
        [
          [
            101642.0,
            348527.0
          ]
        ]
      ],
      [
        [
          [
            -139354.0,
            289054.0
          ],
          [
            75525.0,
            -334881.0
          ],
          [
            388361.0,
            -939945.0
          ],
          [
            438320.0,
            -934423.0
          ],
          [
            448575.0,
            310579.0
          ],
          [
            240954.0,
            759902.0
          ],
          [
            -25099.0,
            790631.0
          ]
        ],
        [
          [
            -101913.0,
            261028.0
          ],
          [
            252012.0,
            -440318.0
          ],
          [
            356160.0,
            -448375.0
          ],
          [
            446542.0,
            146316.0
          ],
          [
            160478.0,
            679861.0
          ],
          [
            -31060.0,
            577821.0
          ]
        ],
        [
          [
            101642.0,
            348527.0
          ]
        ]
      ],
      [
        [
          [
            -139354.0,
            289054.0
          ],
          [
            75525.0,
            -334881.0
          ],
          [
            388361.0,
            -939945.0
          ],
          [
            438320.0,
            -934423.0
          ],
          [
            448575.0,
            310579.0
          ],
          [
            240954.0,
            759902.0
          ],
          [
            -31060.0,
            577821.0
          ]
        ],
        [
          [
            -101913.0,
            261028.0
          ],
          [
            252012.0,
            -440318.0
          ],
          [
            356160.0,
            -448375.0
          ],
          [
            446542.0,
            146316.0
          ],
          [
            160478.0,
            679861.0
          ]
        ],
        [
          [
            101642.0,
            348527.0
          ]
        ]
      ],
      [
        [
          [
            -139354.0,
            289054.0
          ],
          [
            388361.0,
            -939945.0
          ],
          [
            438320.0,
            -934423.0
          ],
          [
            448575.0,
            310579.0
          ],
          [
            240954.0,
            759902.0
          ],
          [
            -31060.0,
            577821.0
          ]
        ],
        [
          [
            -101913.0,
            261028.0
          ],
          [
            252012.0,
            -440318.0
          ],
          [
            356160.0,
            -448375.0
          ],
          [
            446542.0,
            146316.0
          ],
          [
            160478.0,
            679861.0
          ]
        ],
        [
          [
            101642.0,
            348527.0
          ]
        ]
      ],
      [
        [
          [
            -139354.0,
            289054.0
          ],
          [
            438320.0,
            -934423.0
          ],
          [
            448575.0,
            310579.0
          ],
          [
            240954.0,
            759902.0
          ],
          [
            -31060.0,
            577821.0
          ]
        ],
        [
          [
            -101913.0,
            261028.0
          ],
          [
            252012.0,
            -440318.0
          ],
          [
            356160.0,
            -448375.0
          ],
          [
            446542.0,
            146316.0
          ],
          [
            160478.0,
            679861.0
          ]
        ],
        [
          [
            101642.0,
            348527.0
          ]
        ]
      ],
      [
        [
          [
            -139354.0,
            289054.0
          ],
          [
            252012.0,
            -440318.0
          ],
          [
            356160.0,
            -448375.0
          ],
          [
            446542.0,
            146316.0
          ],
          [
            448575.0,
            310579.0
          ],
          [
            240954.0,
            759902.0
          ],
          [
            -31060.0,
            577821.0
          ]
        ],
        [
          [
            -101913.0,
            261028.0
          ],
          [
            101642.0,
            348527.0
          ],
          [
            160478.0,
            679861.0
          ]
        ]
      ],
      [
        [
          [
            -139354.0,
            289054.0
          ],
          [
            356160.0,
            -448375.0
          ],
          [
            446542.0,
            146316.0
          ],
          [
            448575.0,
            310579.0
          ],
          [
            240954.0,
            759902.0
          ],
          [
            -31060.0,
            577821.0
          ]
        ],
        [
          [
            -101913.0,
            261028.0
          ],
          [
            101642.0,
            348527.0
          ],
          [
            160478.0,
            679861.0
          ]
        ]
      ],
      [
        [
          [
            -139354.0,
            289054.0
          ],
          [
            -101913.0,
            261028.0
          ],
          [
            446542.0,
            146316.0
          ],
          [
            448575.0,
            310579.0
          ],
          [
            240954.0,
            759902.0
          ],
          [
            -31060.0,
            577821.0
          ]
        ],
        [
          [
            101642.0,
            348527.0
          ],
          [
            160478.0,
            679861.0
          ]
        ]
      ],
      [
        [
          [
            -139354.0,
            289054.0
          ],
          [
            -101913.0,
            261028.0
          ],
          [
            448575.0,
            310579.0
          ],
          [
            240954.0,
            759902.0
          ],
          [
            -31060.0,
            577821.0
          ]
        ],
        [
          [
            101642.0,
            348527.0
          ],
          [
            160478.0,
            679861.0
          ]
        ]
      ],
      [
        [
          [
            -139354.0,
            289054.0
          ],
          [
            -101913.0,
            261028.0
          ],
          [
            101642.0,
            348527.0
          ],
          [
            240954.0,
            759902.0
          ],
          [
            -31060.0,
            577821.0
          ]
        ],
        [
          [
            160478.0,
            679861.0
          ]
        ]
      ],
      [
        [
          [
            -139354.0,
            289054.0
          ],
          [
            -101913.0,
            261028.0
          ],
          [
            240954.0,
            759902.0
          ],
          [
            -31060.0,
            577821.0
          ]
        ],
        [
          [
            160478.0,
            679861.0
          ]
        ]
      ],
      [
        [
          [
            -139354.0,
            289054.0
          ],
          [
            -101913.0,
            261028.0
          ],
          [
            240954.0,
            759902.0
          ],
          [
            160478.0,
            679861.0
          ]
        ]
      ],
      [
        [
          [
            -139354.0,
            289054.0
          ],
          [
            240954.0,
            759902.0
          ],
          [
            160478.0,
            679861.0
          ]
        ]
      ]
    ]
  },
  "metadata": {
    "seed": 1230,
    "point_count": 25,
    "grid_limit": 1000000,
    "rejected_attempts": 0,
    "convex_hull_algorithm": "andrews_monotone_chain",
    "epsilons": {
      "orientation_epsilon": 1e-09,
      "min_area_decrease_epsilon": 1e-09
    },
    "source_suite": "v1_gold",
    "layer_snapshot_rule": "layers_after_peel"
  }
}
