{
  "case_id": "case_0856",
  "points": [
    [
      843046.0,
      184787.0
    ],
    [
      526636.0,
      273702.0
    ],
    [
      -99020.0,
      -698559.0
    ],
    [
      -386495.0,
      -121024.0
    ],
    [
      -64106.0,
      307149.0
    ],
    [
      196572.0,
      151182.0
    ],
    [
      117821.0,
      50607.0
    ],
    [
      469633.0,
      687921.0
    ],
    [
      738160.0,
      -170369.0
    ],
    [
      -943565.0,
      224425.0
    ],
    [
      522353.0,
      84630.0
    ],
    [
      155349.0,
      -888770.0
    ],
    [
      823508.0,
      261778.0
    ],
    [
      920775.0,
      231868.0
    ],
    [
      449106.0,
      786751.0
    ],
    [
      -907674.0,
      -190365.0
    ],
    [
      -36441.0,
      -313750.0
    ],
    [
      908557.0,
      -608777.0
    ],
    [
      -62842.0,
      517195.0
    ],
    [
      -772046.0,
      -571064.0
    ],
    [
      -552313.0,
      380563.0
    ],
    [
      84848.0,
      190376.0
    ],
    [
      -390050.0,
      -168576.0
    ],
    [
      -271062.0,
      518118.0
    ],
    [
      -88209.0,
      -779183.0
    ]
  ],
  "expected": {
    "peel_order": [
      [
        908557.0,
        -608777.0
      ],
      [
        155349.0,
        -888770.0
      ],
      [
        -772046.0,
        -571064.0
      ],
      [
        -907674.0,
        -190365.0
      ],
      [
        -943565.0,
        224425.0
      ],
      [
        738160.0,
        -170369.0
      ],
      [
        -552313.0,
        380563.0
      ],
      [
        -271062.0,
        518118.0
      ],
      [
        -62842.0,
        517195.0
      ],
      [
        -88209.0,
        -779183.0
      ],
      [
        -99020.0,
        -698559.0
      ],
      [
        -36441.0,
        -313750.0
      ],
      [
        449106.0,
        786751.0
      ],
      [
        469633.0,
        687921.0
      ],
      [
        -64106.0,
        307149.0
      ],
      [
        84848.0,
        190376.0
      ],
      [
        -390050.0,
        -168576.0
      ],
      [
        -386495.0,
        -121024.0
      ],
      [
        526636.0,
        273702.0
      ],
      [
        196572.0,
        151182.0
      ],
      [
        117821.0,
        50607.0
      ],
      [
        522353.0,
        84630.0
      ]
    ],
    "area_decreases": [
      263261117547.0,
      131545708866.0,
      116054649165.5,
      159386310256.0,
      234724085654.0,
      110608809421.5,
      86774529824.0,
      94894085111.5,
      87183610023.0,
      55006577442.0,
      238350763687.5,
      146891830129.0,
      47895248071.5,
      196530040054.0,
      84155266521.5,
      39944812019.0,
      21243220063.0,
      44738678621.5,
      20154220288.0,
      27172271302.0,
      30707919085.5,
      13323671114.5
    ],
    "hulls": [
      [
        [
          -943565.0,
          224425.0
        ],
        [
          -907674.0,
          -190365.0
        ],
        [
          -772046.0,
          -571064.0
        ],
        [
          155349.0,
          -888770.0
        ],
        [
          908557.0,
          -608777.0
        ],
        [
          920775.0,
          231868.0
        ],
        [
          449106.0,
          786751.0
        ],
        [
          -271062.0,
          518118.0
        ]
      ],
      [
        [
          -943565.0,
          224425.0
        ],
        [
          -907674.0,
          -190365.0
        ],
        [
          -772046.0,
          -571064.0
        ],
        [
          155349.0,
          -888770.0
        ],
        [
          738160.0,
          -170369.0
        ],
        [
          920775.0,
          231868.0
        ],
        [
          449106.0,
          786751.0
        ],
        [
          -271062.0,
          518118.0
        ]
      ],
      [
        [
          -943565.0,
          224425.0
        ],
        [
          -907674.0,
          -190365.0
        ],
        [
          -772046.0,
          -571064.0
        ],
        [
          -88209.0,
          -779183.0
        ],
        [
          738160.0,
          -170369.0
        ],
        [
          920775.0,
          231868.0
        ],
        [
          449106.0,
          786751.0
        ],
        [
          -271062.0,
          518118.0
        ]
      ],
      [
        [
          -943565.0,
          224425.0
        ],
        [
          -907674.0,
          -190365.0
        ],
        [
          -88209.0,
          -779183.0
        ],
        [
          738160.0,
          -170369.0
        ],
        [
          920775.0,
          231868.0
        ],
        [
          449106.0,
          786751.0
        ],
        [
          -271062.0,
          518118.0
        ]
      ],
      [
        [
          -943565.0,
          224425.0
        ],
        [
          -88209.0,
          -779183.0
        ],
        [
          738160.0,
          -170369.0
        ],
        [
          920775.0,
          231868.0
        ],
        [
          449106.0,
          786751.0
        ],
        [
          -271062.0,
          518118.0
        ]
      ],
      [
        [
          -552313.0,
          380563.0
        ],
        [
          -390050.0,
          -168576.0
        ],
        [
          -88209.0,
          -779183.0
        ],
        [
          738160.0,
          -170369.0
        ],
        [
          920775.0,
          231868.0
        ],
        [
          449106.0,
          786751.0
        ],
        [
          -271062.0,
          518118.0
        ]
      ],
      [
        [
          -552313.0,
          380563.0
        ],
        [
          -390050.0,
          -168576.0
        ],
        [
          -88209.0,
          -779183.0
        ],
        [
          920775.0,
          231868.0
        ],
        [
          449106.0,
          786751.0
        ],
        [
          -271062.0,
          518118.0
        ]
      ],
      [
        [
          -390050.0,
          -168576.0
        ],
        [
          -88209.0,
          -779183.0
        ],
        [
          920775.0,
          231868.0
        ],
        [
          449106.0,
          786751.0
        ],
        [
          -271062.0,
          518118.0
        ],
        [
          -386495.0,
          -121024.0
        ]
      ],
      [
        [
          -390050.0,
          -168576.0
        ],
        [
          -88209.0,
          -779183.0
        ],
        [
          920775.0,
          231868.0
        ],
        [
          449106.0,
          786751.0
        ],
        [
          -62842.0,
          517195.0
        ],
        [
          -386495.0,
          -121024.0
        ]
      ],
      [
        [
          -390050.0,
          -168576.0
        ],
        [
          -88209.0,
          -779183.0
        ],
        [
          920775.0,
          231868.0
        ],
        [
          449106.0,
          786751.0
        ],
        [
          -64106.0,
          307149.0
        ],
        [
          -386495.0,
          -121024.0
        ]
      ],
      [
        [
          -390050.0,
          -168576.0
        ],
        [
          -99020.0,
          -698559.0
        ],
        [
          920775.0,
          231868.0
        ],
        [
          449106.0,
          786751.0
        ],
        [
          -64106.0,
          307149.0
        ],
        [
          -386495.0,
          -121024.0
        ]
      ],
      [
        [
          -390050.0,
          -168576.0
        ],
        [
          -36441.0,
          -313750.0
        ],
        [
          843046.0,
          184787.0
        ],
        [
          920775.0,
          231868.0
        ],
        [
          449106.0,
          786751.0
        ],
        [
          -64106.0,
          307149.0
        ],
        [
          -386495.0,
          -121024.0
        ]
      ],
      [
        [
          -390050.0,
          -168576.0
        ],
        [
          522353.0,
          84630.0
        ],
        [
          843046.0,
          184787.0
        ],
        [
          920775.0,
          231868.0
        ],
        [
          449106.0,
          786751.0
        ],
        [
          -64106.0,
          307149.0
        ],
        [
          -386495.0,
          -121024.0
        ]
      ],
      [
        [
          -390050.0,
          -168576.0
        ],
        [
          522353.0,
          84630.0
        ],
        [
          843046.0,
          184787.0
        ],
        [
          920775.0,
          231868.0
        ],
        [
          469633.0,
          687921.0
        ],
        [
          -64106.0,
          307149.0
        ],
        [
          -386495.0,
          -121024.0
        ]
      ],
      [
        [
          -390050.0,
          -168576.0
        ],
        [
          522353.0,
          84630.0
        ],
        [
          843046.0,
          184787.0
        ],
        [
          920775.0,
          231868.0
        ],
        [
          823508.0,
          261778.0
        ],
        [
          -64106.0,
          307149.0
        ],
        [
          -386495.0,
          -121024.0
        ]
      ],
      [
        [
          -390050.0,
          -168576.0
        ],
        [
          522353.0,
          84630.0
        ],
        [
          843046.0,
          184787.0
        ],
        [
          920775.0,
          231868.0
        ],
        [
          823508.0,
          261778.0
        ],
        [
          526636.0,
          273702.0
        ],
        [
          84848.0,
          190376.0
        ],
        [
          -386495.0,
          -121024.0
        ]
      ],
      [
        [
          -390050.0,
          -168576.0
        ],
        [
          522353.0,
          84630.0
        ],
        [
          843046.0,
          184787.0
        ],
        [
          920775.0,
          231868.0
        ],
        [
          823508.0,
          261778.0
        ],
        [
          526636.0,
          273702.0
        ],
        [
          196572.0,
          151182.0
        ],
        [
          -386495.0,
          -121024.0
        ]
      ],
      [
        [
          -386495.0,
          -121024.0
        ],
        [
          522353.0,
          84630.0
        ],
        [
          843046.0,
          184787.0
        ],
        [
          920775.0,
          231868.0
        ],
        [
          823508.0,
          261778.0
        ],
        [
          526636.0,
          273702.0
        ],
        [
          196572.0,
          151182.0
        ]
      ],
      [
        [
          117821.0,
          50607.0
        ],
        [
          522353.0,
          84630.0
        ],
        [
          843046.0,
          184787.0
        ],
        [
          920775.0,
          231868.0
        ],
        [
          823508.0,
          261778.0
        ],
        [
          526636.0,
          273702.0
        ],
        [
          196572.0,
          151182.0
        ]
      ],
      [
        [
          117821.0,
          50607.0
        ],
        [
          522353.0,
          84630.0
        ],
        [
          843046.0,
          184787.0
        ],
        [
          920775.0,
          231868.0
        ],
        [
          823508.0,
          261778.0
        ],
        [
          196572.0,
          151182.0
        ]
      ],
      [
        [
          117821.0,
          50607.0
        ],
        [
          522353.0,
          84630.0
        ],
        [
          843046.0,
          184787.0
        ],
        [
          920775.0,
          231868.0
        ],
        [
          823508.0,
          261778.0
        ]
      ],
      [
        [
          522353.0,
          84630.0
        ],
        [
          843046.0,
          184787.0
        ],
        [
          920775.0,
          231868.0
        ],
        [
          823508.0,
          261778.0
        ]
      ]
    ],
    "final_points": [
      [
        843046.0,
        184787.0
      ],
      [
        823508.0,
        261778.0
      ],
      [
        920775.0,
        231868.0
      ]
    ]
  },
  "metadata": {
    "seed": 1855,
    "point_count": 25,
    "grid_limit": 1000000,
    "rejected_attempts": 0,
    "convex_hull_algorithm": "andrews_monotone_chain",
    "epsilons": {
      "orientation_epsilon": 1e-09,
      "min_area_decrease_epsilon": 1e-09
    }
  }
}
